{
    "client": "Thunder Client",
    "collectionName": "studio-tsar",
    "dateExported": "2023-03-18T22:34:20.603Z",
    "version": "1.1",
    "folders": [
        {
            "_id": "b191a313-7136-4dc6-944b-dfaf3a66ec33",
            "name": "studios",
            "containerId": "",
            "created": "2023-03-16T23:23:59.283Z",
            "sortNum": 10000
        },
        {
            "_id": "9a843ca2-e5be-4609-9a5b-fed80cc8511c",
            "name": "projects",
            "containerId": "b191a313-7136-4dc6-944b-dfaf3a66ec33",
            "created": "2023-03-18T12:11:10.588Z",
            "sortNum": 20000
        },
        {
            "_id": "8a8eb155-492d-4e9b-a2ca-72ce0f55265c",
            "name": "appointments",
            "containerId": "9a843ca2-e5be-4609-9a5b-fed80cc8511c",
            "created": "2023-03-18T16:07:02.185Z",
            "sortNum": 30000
        },
        {
            "_id": "e40aedde-3b89-41d6-b90a-497d07f99142",
            "name": "billing",
            "containerId": "9a843ca2-e5be-4609-9a5b-fed80cc8511c",
            "created": "2023-03-18T16:07:08.710Z",
            "sortNum": 40000
        },
        {
            "_id": "fae6a5a6-3a14-4815-afb5-94430892f095",
            "name": "documents",
            "containerId": "9a843ca2-e5be-4609-9a5b-fed80cc8511c",
            "created": "2023-03-18T16:07:16.846Z",
            "sortNum": 50000
        },
        {
            "_id": "97ec3273-6520-465a-8378-8f21ae511a38",
            "name": "events",
            "containerId": "b191a313-7136-4dc6-944b-dfaf3a66ec33",
            "created": "2023-03-18T22:28:07.193Z",
            "sortNum": 60000
        },
        {
            "_id": "38844d05-4bfa-4127-84e0-26e6ad38b611",
            "name": "users",
            "containerId": "",
            "created": "2023-03-18T16:34:47.914Z",
            "sortNum": 70000
        },
        {
            "_id": "c6a52a17-7a63-4362-b6cb-49d4a7e9ccee",
            "name": "artists",
            "containerId": "38844d05-4bfa-4127-84e0-26e6ad38b611",
            "created": "2023-03-18T16:34:55.361Z",
            "sortNum": 80000
        },
        {
            "_id": "c838c42c-05ed-454a-bfe5-21c4881d75c7",
            "name": "clients",
            "containerId": "38844d05-4bfa-4127-84e0-26e6ad38b611",
            "created": "2023-03-18T16:35:02.561Z",
            "sortNum": 90000
        },
        {
            "_id": "5c6c4e38-861e-45e0-917f-bf1fa0d9b6b4",
            "name": "clients",
            "containerId": "b191a313-7136-4dc6-944b-dfaf3a66ec33",
            "created": "2023-03-18T18:22:08.817Z",
            "sortNum": 100000
        },
        {
            "_id": "e09e4f1c-704b-49db-b2e3-34b59961a8e7",
            "name": "artists",
            "containerId": "b191a313-7136-4dc6-944b-dfaf3a66ec33",
            "created": "2023-03-18T18:22:16.206Z",
            "sortNum": 110000
        }
    ],
    "requests": [
        {
            "_id": "efc7d267-9f4f-4b6d-a24d-2fa07549e923",
            "colId": "da95575f-f1d7-4fb9-a447-028b849cb4d1",
            "containerId": "b191a313-7136-4dc6-944b-dfaf3a66ec33",
            "name": "create",
            "url": "/studios/create",
            "method": "POST",
            "sortNum": 10000,
            "created": "2023-03-16T23:24:10.152Z",
            "modified": "2023-03-18T12:10:51.767Z",
            "headers": [],
            "params": [],
            "tests": []
        },
        {
            "_id": "5fb86087-6f9c-4da9-a294-128c7bb24f69",
            "colId": "da95575f-f1d7-4fb9-a447-028b849cb4d1",
            "containerId": "e40aedde-3b89-41d6-b90a-497d07f99142",
            "name": "create",
            "url": "/studios/{{studioId}}/projects/{{projectId}}/bills/create",
            "method": "POST",
            "sortNum": 10000,
            "created": "2023-03-18T16:14:38.222Z",
            "modified": "2023-03-18T22:20:18.403Z",
            "headers": [],
            "params": [],
            "tests": []
        },
        {
            "_id": "a0b781f4-31d7-4c93-afce-b1faa6ad9a92",
            "colId": "da95575f-f1d7-4fb9-a447-028b849cb4d1",
            "containerId": "8a8eb155-492d-4e9b-a2ca-72ce0f55265c",
            "name": "create",
            "url": "/studios/{{studioId}}/projects/{{projectId}}/appointments/add",
            "method": "POST",
            "sortNum": 10000,
            "created": "2023-03-18T19:56:18.201Z",
            "modified": "2023-03-18T22:21:29.554Z",
            "headers": [],
            "params": [],
            "tests": []
        },
        {
            "_id": "39ba8a64-65e4-4493-92d5-84eab973ea9d",
            "colId": "da95575f-f1d7-4fb9-a447-028b849cb4d1",
            "containerId": "9a843ca2-e5be-4609-9a5b-fed80cc8511c",
            "name": "create",
            "url": "/studios/{{studioId}}/projects/create",
            "method": "POST",
            "sortNum": 20000,
            "created": "2023-03-18T12:11:23.888Z",
            "modified": "2023-03-18T22:19:06.261Z",
            "headers": [],
            "params": [],
            "tests": []
        },
        {
            "_id": "c5f2cfd3-299d-4d42-a13f-36646304f818",
            "colId": "da95575f-f1d7-4fb9-a447-028b849cb4d1",
            "containerId": "e40aedde-3b89-41d6-b90a-497d07f99142",
            "name": "delete",
            "url": "/studios/{{studioId}}/projects/{{projectId}}/bills/{{billId}}/delete",
            "method": "DELETE",
            "sortNum": 20000,
            "created": "2023-03-18T16:14:48.871Z",
            "modified": "2023-03-18T22:19:56.760Z",
            "headers": [],
            "params": [],
            "tests": []
        },
        {
            "_id": "a52efb4a-c38b-41e3-897a-9f8734cd6e8f",
            "colId": "da95575f-f1d7-4fb9-a447-028b849cb4d1",
            "containerId": "8a8eb155-492d-4e9b-a2ca-72ce0f55265c",
            "name": "delete",
            "url": "/studios/{{studioId}}/projects/{{projectId}}/appointments/{{appointmentId}}/delete",
            "method": "DELETE",
            "sortNum": 20000,
            "created": "2023-03-18T19:56:22.273Z",
            "modified": "2023-03-18T22:21:12.449Z",
            "headers": [],
            "params": [],
            "tests": []
        },
        {
            "_id": "09108e90-c1f2-4f3e-9fa0-ccfe72124801",
            "colId": "da95575f-f1d7-4fb9-a447-028b849cb4d1",
            "containerId": "e09e4f1c-704b-49db-b2e3-34b59961a8e7",
            "name": "search",
            "url": "/studios/{{studioId}}/artists/search",
            "method": "GET",
            "sortNum": 20000,
            "created": "2023-03-18T22:27:10.616Z",
            "modified": "2023-03-18T22:27:24.651Z",
            "headers": [],
            "params": [],
            "tests": []
        },
        {
            "_id": "b3c0d186-f11c-4180-b351-afcb70cac929",
            "colId": "da95575f-f1d7-4fb9-a447-028b849cb4d1",
            "containerId": "97ec3273-6520-465a-8378-8f21ae511a38",
            "name": "search",
            "url": "/studios/{{studioId}}/events/search",
            "method": "GET",
            "sortNum": 20000,
            "created": "2023-03-18T22:28:07.193Z",
            "modified": "2023-03-18T22:28:30.328Z",
            "headers": [],
            "params": [],
            "tests": []
        },
        {
            "_id": "baddec16-61a6-4d7d-89f7-fd302d3eed41",
            "colId": "da95575f-f1d7-4fb9-a447-028b849cb4d1",
            "containerId": "9a843ca2-e5be-4609-9a5b-fed80cc8511c",
            "name": "search",
            "url": "/studios/{{studioId}}/projects/{{projectId}}/documents/search",
            "method": "GET",
            "sortNum": 25000,
            "created": "2023-03-18T22:24:29.590Z",
            "modified": "2023-03-18T22:24:40.547Z",
            "headers": [],
            "params": [],
            "tests": []
        },
        {
            "_id": "a14f4ac1-66ee-4396-8e4d-0c3fa48cdd99",
            "colId": "da95575f-f1d7-4fb9-a447-028b849cb4d1",
            "containerId": "9a843ca2-e5be-4609-9a5b-fed80cc8511c",
            "name": "edit",
            "url": "/studios/{{studioId}}/projects/{{projectId}}/documents/{{documentId}}/edit",
            "method": "PUT",
            "sortNum": 30000,
            "created": "2023-03-18T12:13:16.037Z",
            "modified": "2023-03-18T19:58:24.481Z",
            "headers": [],
            "params": [],
            "tests": []
        },
        {
            "_id": "a4ad3c45-e438-488d-98ae-407e9ed83a78",
            "colId": "da95575f-f1d7-4fb9-a447-028b849cb4d1",
            "containerId": "e40aedde-3b89-41d6-b90a-497d07f99142",
            "name": "edit",
            "url": "/studios/{{studioId}}/projects/{{projectId}}/bills/{{billId}}/edit",
            "method": "PUT",
            "sortNum": 30000,
            "created": "2023-03-18T16:14:53.023Z",
            "modified": "2023-03-18T20:02:15.691Z",
            "headers": [],
            "params": [],
            "tests": []
        },
        {
            "_id": "4840d592-54b6-403b-8d32-8b7143add2d1",
            "colId": "da95575f-f1d7-4fb9-a447-028b849cb4d1",
            "containerId": "8a8eb155-492d-4e9b-a2ca-72ce0f55265c",
            "name": "edit",
            "url": "/studios/{{studioId}}/projects/{{projectId}}/appointments/{{appointmentId}}/edit",
            "method": "PUT",
            "sortNum": 30000,
            "created": "2023-03-18T19:56:27.841Z",
            "modified": "2023-03-18T22:20:49.442Z",
            "headers": [],
            "params": [],
            "tests": []
        },
        {
            "_id": "9d4c3790-53a5-42d2-8ba4-04d3250d492d",
            "colId": "da95575f-f1d7-4fb9-a447-028b849cb4d1",
            "containerId": "b191a313-7136-4dc6-944b-dfaf3a66ec33",
            "name": "edit",
            "url": "/studios/{{studioId}}/edit",
            "method": "PUT",
            "sortNum": 40000,
            "created": "2023-03-18T12:17:56.140Z",
            "modified": "2023-03-18T19:49:13.007Z",
            "headers": [],
            "params": [],
            "tests": []
        },
        {
            "_id": "e221527e-a8d2-4a7a-af06-f335259b25ea",
            "colId": "da95575f-f1d7-4fb9-a447-028b849cb4d1",
            "containerId": "e09e4f1c-704b-49db-b2e3-34b59961a8e7",
            "name": "remove",
            "url": "/studios/{{studioId}}/artists/{{studioArtistId}}/remove",
            "method": "DELETE",
            "sortNum": 40000,
            "created": "2023-03-18T20:07:35.090Z",
            "modified": "2023-03-18T20:10:36.402Z",
            "headers": [],
            "params": [],
            "tests": []
        },
        {
            "_id": "4d2b1707-05b7-4895-a6f1-960ba3665dfe",
            "colId": "da95575f-f1d7-4fb9-a447-028b849cb4d1",
            "containerId": "97ec3273-6520-465a-8378-8f21ae511a38",
            "name": "remove",
            "url": "/studios/{{studioId}}/events/{{eventId}}/remove",
            "method": "DELETE",
            "sortNum": 40000,
            "created": "2023-03-18T22:28:07.194Z",
            "modified": "2023-03-18T22:28:45.851Z",
            "headers": [],
            "params": [],
            "tests": []
        },
        {
            "_id": "0bdc910a-a383-4f88-b494-ab953af51a93",
            "colId": "da95575f-f1d7-4fb9-a447-028b849cb4d1",
            "containerId": "b191a313-7136-4dc6-944b-dfaf3a66ec33",
            "name": "search",
            "url": "/studios/search",
            "method": "GET",
            "sortNum": 50000,
            "created": "2023-03-18T15:55:43.619Z",
            "modified": "2023-03-18T15:55:51.930Z",
            "headers": [],
            "params": [],
            "tests": []
        },
        {
            "_id": "8c6cb34f-f5da-4b5e-971d-926ac8de46aa",
            "colId": "da95575f-f1d7-4fb9-a447-028b849cb4d1",
            "containerId": "fae6a5a6-3a14-4815-afb5-94430892f095",
            "name": "create",
            "url": "/studios/123/projects/123/documents/create",
            "method": "POST",
            "sortNum": 60000,
            "created": "2023-03-18T16:07:28.813Z",
            "modified": "2023-03-18T16:07:54.632Z",
            "headers": [],
            "params": [],
            "tests": []
        },
        {
            "_id": "24423b08-e26a-4f76-b55c-542ce389ffde",
            "colId": "da95575f-f1d7-4fb9-a447-028b849cb4d1",
            "containerId": "fae6a5a6-3a14-4815-afb5-94430892f095",
            "name": "delete",
            "url": "/studios/123/projects/123/documents/123/delete",
            "method": "DELETE",
            "sortNum": 70000,
            "created": "2023-03-18T16:11:22.523Z",
            "modified": "2023-03-18T16:12:29.965Z",
            "headers": [],
            "params": [],
            "tests": []
        },
        {
            "_id": "a2cb2870-3d82-49a8-9e45-96c1087dc83f",
            "colId": "da95575f-f1d7-4fb9-a447-028b849cb4d1",
            "containerId": "fae6a5a6-3a14-4815-afb5-94430892f095",
            "name": "edit",
            "url": "/studios/123/projects/123/documents/123/edit",
            "method": "PUT",
            "sortNum": 80000,
            "created": "2023-03-18T16:13:19.925Z",
            "modified": "2023-03-18T16:13:56.950Z",
            "headers": [],
            "params": [],
            "tests": []
        },
        {
            "_id": "8bdeb136-f4d5-4872-af70-058dcabd88c5",
            "colId": "da95575f-f1d7-4fb9-a447-028b849cb4d1",
            "containerId": "e09e4f1c-704b-49db-b2e3-34b59961a8e7",
            "name": "edit",
            "url": "/studios/{{studioId}}/artists/{{studioArtistId}}/edit",
            "method": "PUT",
            "sortNum": 80000,
            "created": "2023-03-18T20:07:26.746Z",
            "modified": "2023-03-18T20:08:41.605Z",
            "headers": [],
            "params": [],
            "tests": []
        },
        {
            "_id": "8c82aeca-4562-4fed-ac12-b02bb6ab8d93",
            "colId": "da95575f-f1d7-4fb9-a447-028b849cb4d1",
            "containerId": "97ec3273-6520-465a-8378-8f21ae511a38",
            "name": "edit",
            "url": "/studios/{{studioId}}/events/{{eventId}}/edit",
            "method": "PUT",
            "sortNum": 80000,
            "created": "2023-03-18T22:28:07.195Z",
            "modified": "2023-03-18T22:29:14.367Z",
            "headers": [],
            "params": [],
            "tests": []
        },
        {
            "_id": "c93732d0-12e9-4137-baa3-2a9968aa2f94",
            "colId": "da95575f-f1d7-4fb9-a447-028b849cb4d1",
            "containerId": "c6a52a17-7a63-4362-b6cb-49d4a7e9ccee",
            "name": "create",
            "url": "/artists/create",
            "method": "POST",
            "sortNum": 90000,
            "created": "2023-03-18T16:35:09.232Z",
            "modified": "2023-03-18T16:58:30.570Z",
            "headers": [],
            "params": [],
            "tests": []
        },
        {
            "_id": "fe36b7ae-6ce6-48ab-a951-9c639b8a8e9a",
            "colId": "da95575f-f1d7-4fb9-a447-028b849cb4d1",
            "containerId": "c838c42c-05ed-454a-bfe5-21c4881d75c7",
            "name": "create",
            "url": "/clients/create",
            "method": "POST",
            "sortNum": 100000,
            "created": "2023-03-18T16:58:40.905Z",
            "modified": "2023-03-18T16:58:59.956Z",
            "headers": [],
            "params": [],
            "tests": []
        },
        {
            "_id": "4c2d53f6-6c4e-45e9-a0c4-9aabb4c2b661",
            "colId": "da95575f-f1d7-4fb9-a447-028b849cb4d1",
            "containerId": "c6a52a17-7a63-4362-b6cb-49d4a7e9ccee",
            "name": "edit",
            "url": "/artists/123/edit",
            "method": "PUT",
            "sortNum": 110000,
            "created": "2023-03-18T16:59:08.447Z",
            "modified": "2023-03-18T17:03:54.479Z",
            "headers": [],
            "params": [],
            "tests": []
        },
        {
            "_id": "3dfabaf8-853f-4ad5-a6dd-10fe00005f03",
            "colId": "da95575f-f1d7-4fb9-a447-028b849cb4d1",
            "containerId": "c838c42c-05ed-454a-bfe5-21c4881d75c7",
            "name": "edit",
            "url": "/clients/123/edit",
            "method": "PUT",
            "sortNum": 110000,
            "created": "2023-03-18T17:00:57.817Z",
            "modified": "2023-03-18T17:02:40.306Z",
            "headers": [],
            "params": [],
            "tests": []
        },
        {
            "_id": "a6aaf759-1154-413b-a769-d19f52da77f3",
            "colId": "da95575f-f1d7-4fb9-a447-028b849cb4d1",
            "containerId": "c6a52a17-7a63-4362-b6cb-49d4a7e9ccee",
            "name": "remove",
            "url": "/artists/{{artistId}}/remove",
            "method": "DELETE",
            "sortNum": 120000,
            "created": "2023-03-18T16:59:45.306Z",
            "modified": "2023-03-18T20:19:05.084Z",
            "headers": [],
            "params": [],
            "tests": []
        },
        {
            "_id": "1704cd1b-ed54-4942-880e-eb5ca888f1c4",
            "colId": "da95575f-f1d7-4fb9-a447-028b849cb4d1",
            "containerId": "c838c42c-05ed-454a-bfe5-21c4881d75c7",
            "name": "remove",
            "url": "/clients/123/remove",
            "method": "DELETE",
            "sortNum": 120000,
            "created": "2023-03-18T17:01:04.608Z",
            "modified": "2023-03-18T17:12:39.118Z",
            "headers": [],
            "params": [],
            "tests": []
        },
        {
            "_id": "0c06d63e-7f53-4609-8278-23096a6a26bb",
            "colId": "da95575f-f1d7-4fb9-a447-028b849cb4d1",
            "containerId": "c6a52a17-7a63-4362-b6cb-49d4a7e9ccee",
            "name": "validate",
            "url": "/artists/{{artistId}}/validate",
            "method": "PUT",
            "sortNum": 130000,
            "created": "2023-03-18T17:00:29.236Z",
            "modified": "2023-03-18T20:19:11.788Z",
            "headers": [],
            "params": [],
            "tests": []
        },
        {
            "_id": "05d76617-45e3-4d00-a7e9-dc2308633e11",
            "colId": "da95575f-f1d7-4fb9-a447-028b849cb4d1",
            "containerId": "c838c42c-05ed-454a-bfe5-21c4881d75c7",
            "name": "validate",
            "url": "/clients/123/validate",
            "method": "PUT",
            "sortNum": 130000,
            "created": "2023-03-18T17:01:10.224Z",
            "modified": "2023-03-18T17:03:17.510Z",
            "headers": [],
            "params": [],
            "tests": []
        },
        {
            "_id": "47758d41-53df-4fb8-b67c-99479fe639d7",
            "colId": "da95575f-f1d7-4fb9-a447-028b849cb4d1",
            "containerId": "5c6c4e38-861e-45e0-917f-bf1fa0d9b6b4",
            "name": "add",
            "url": "/studios/123/clients/add",
            "method": "POST",
            "sortNum": 140000,
            "created": "2023-03-18T18:23:37.240Z",
            "modified": "2023-03-18T19:11:58.783Z",
            "headers": [],
            "params": [],
            "tests": []
        },
        {
            "_id": "b578433a-9913-4584-b546-01449dd3c254",
            "colId": "da95575f-f1d7-4fb9-a447-028b849cb4d1",
            "containerId": "b191a313-7136-4dc6-944b-dfaf3a66ec33",
            "name": "remove",
            "url": "/studios/{{studioId}}/remove",
            "method": "DELETE",
            "sortNum": 150000,
            "created": "2023-03-18T19:49:49.042Z",
            "modified": "2023-03-18T19:50:42.111Z",
            "headers": [],
            "params": [],
            "tests": []
        },
        {
            "_id": "78c483a1-ea78-484f-b966-5af4426cffaf",
            "colId": "da95575f-f1d7-4fb9-a447-028b849cb4d1",
            "containerId": "e09e4f1c-704b-49db-b2e3-34b59961a8e7",
            "name": "add",
            "url": "/studios/{{studioId}}/artists/add",
            "method": "POST",
            "sortNum": 160000,
            "created": "2023-03-18T20:00:23.349Z",
            "modified": "2023-03-18T20:00:39.901Z",
            "headers": [],
            "params": [],
            "tests": []
        },
        {
            "_id": "d11f2e8f-b258-434a-a313-876e8af5f057",
            "colId": "da95575f-f1d7-4fb9-a447-028b849cb4d1",
            "containerId": "97ec3273-6520-465a-8378-8f21ae511a38",
            "name": "create",
            "url": "/studios/{{studioId}}/events/create",
            "method": "POST",
            "sortNum": 160000,
            "created": "2023-03-18T22:28:07.197Z",
            "modified": "2023-03-18T22:29:33.253Z",
            "headers": [],
            "params": [],
            "tests": []
        },
        {
            "_id": "02c10a93-7765-4a64-9600-fe5fd1ba0b35",
            "colId": "da95575f-f1d7-4fb9-a447-028b849cb4d1",
            "containerId": "5c6c4e38-861e-45e0-917f-bf1fa0d9b6b4",
            "name": "edit",
            "url": "/studios/{{studioId}}/clients/{{clientId}}/edit",
            "method": "PUT",
            "sortNum": 170000,
            "created": "2023-03-18T20:02:58.375Z",
            "modified": "2023-03-18T20:03:40.645Z",
            "headers": [],
            "params": [],
            "tests": []
        },
        {
            "_id": "5c19fca6-0bc1-439c-a4de-a99615efba3a",
            "colId": "da95575f-f1d7-4fb9-a447-028b849cb4d1",
            "containerId": "5c6c4e38-861e-45e0-917f-bf1fa0d9b6b4",
            "name": "remove",
            "url": "/studios/{{studioId}}/clients/{{clientId}}/remove",
            "method": "DELETE",
            "sortNum": 180000,
            "created": "2023-03-18T20:04:45.612Z",
            "modified": "2023-03-18T20:05:23.967Z",
            "headers": [],
            "params": [],
            "tests": []
        },
        {
            "_id": "972526ea-3479-435a-9d9b-ae0c2a482d7d",
            "colId": "da95575f-f1d7-4fb9-a447-028b849cb4d1",
            "containerId": "8a8eb155-492d-4e9b-a2ca-72ce0f55265c",
            "name": "search",
            "url": "/studios/{{studioId}}/projects/{{projectId}}/appointments/search",
            "method": "GET",
            "sortNum": 190000,
            "created": "2023-03-18T22:16:40.429Z",
            "modified": "2023-03-18T22:20:28.234Z",
            "headers": [],
            "params": [],
            "tests": []
        },
        {
            "_id": "1c9828f4-94dc-4150-91e3-1fafa243c69d",
            "colId": "da95575f-f1d7-4fb9-a447-028b849cb4d1",
            "containerId": "5c6c4e38-861e-45e0-917f-bf1fa0d9b6b4",
            "name": "search",
            "url": "/studios/{{studioId}}/clients/search",
            "method": "GET",
            "sortNum": 190000,
            "created": "2023-03-18T22:25:00.861Z",
            "modified": "2023-03-18T22:27:04.003Z",
            "headers": [],
            "params": [],
            "tests": []
        },
        {
            "_id": "ff02991f-ea5d-4326-afed-44b62fc9a524",
            "colId": "da95575f-f1d7-4fb9-a447-028b849cb4d1",
            "containerId": "e40aedde-3b89-41d6-b90a-497d07f99142",
            "name": "search",
            "url": "/studios/{{studioId}}/projects/{{projectId}}/bills/search",
            "method": "GET",
            "sortNum": 200000,
            "created": "2023-03-18T22:18:01.031Z",
            "modified": "2023-03-18T22:19:27.647Z",
            "headers": [],
            "params": [],
            "tests": []
        },
        {
            "_id": "5d494588-3e37-4b75-b281-1c9d79dd5cac",
            "colId": "da95575f-f1d7-4fb9-a447-028b849cb4d1",
            "containerId": "fae6a5a6-3a14-4815-afb5-94430892f095",
            "name": "delete",
            "url": "/studios/{{studioId}}/projects/{{projectId}}/documents/{{documentId}}/delete",
            "method": "DELETE",
            "sortNum": 210000,
            "created": "2023-03-18T22:22:03.759Z",
            "modified": "2023-03-18T22:23:10.565Z",
            "headers": [],
            "params": [],
            "tests": []
        }
    ],
    "settings": {
        "headers": [],
        "tests": [
            {
                "type": "res-code",
                "custom": "",
                "action": "equal",
                "value": "200"
            }
        ],
        "options": {
            "baseUrl": "http://localhost:1234/api"
        },
        "envId": "7eefdfb4-e946-4cb9-a291-468a4398bf86",
        "runOptions": {
            "delay": 50,
            "iterations": 1,
            "dataFilePath": ""
        }
    }
}
